{
	"Arduino_Mega_2560_Rev3" : { 
		
		"Microcontroller" : "ATmega2560",
        "Digital I/O Pins" : 54,
        "Analog Input Pins" : 16,
        "DC Current per I/O Pin" : 20,
        "DC Current for 3.3V Pin" : 50

    },

    "Arduino_Uno_Rev3" : { 
		
		"Microcontroller" : "ATmega328p",
        "Digital I/O Pins" : 14,
        "PWM Digital I/O Pins" : 6,
        "Analog Input Pins" : 6,
        "DC Current per I/O Pin" : 20,
        "DC Current for 3.3V Pin" : 50

    },

    "Arduino_Uno_Rev3_SMD" : { 
		
		"Microcontroller" : "ATmega328p",
        "Digital I/O Pins" : 14,
        "PWM Digital I/O Pins" : 6,
        "Analog Input Pins" : 6,
        "DC Current per I/O Pin" : 20,
        "DC Current for 3.3V Pin" : 50

    },

    "Arduino_Uno_Wifi_Rev2" : { 
		
		"Microcontroller" : "ATmega4809",
        "Digital I/O Pins" : 14,
        "PWM Digital I/O Pins" : 6,
        "Analog Input Pins" : 6,
        "DC Current per I/O Pin" : 20,
        "DC Current for 3.3V Pin" : 50
	
    }
}